treenav/__init__.py
treenav/admin.py
treenav/apps.py
treenav/context_processors.py
treenav/forms.py
treenav/models.py
treenav/signals.py
treenav/urls.py
treenav/views.py
treenav/migrations/0001_initial.py
treenav/migrations/0002_auto_20151001_1646.py
treenav/migrations/0003_mptt_drop_indexes.py
treenav/migrations/__init__.py
treenav/templates/admin/treenav/menuitem/change_list.html
treenav/templates/treenav/menucrumbs.html
treenav/templates/treenav/menuitem.html
treenav/templatetags/__init__.py
treenav/templatetags/treenav_tags.py
treenav/tests/__init__.py
treenav/tests/base.py
treenav/tests/models.py
treenav/tests/test_models.py
treenav/tests/test_templatetags.py
treenav/tests/test_views.py
treenav/tests/urls.py
django_treenav-2.0.0.dist-info/AUTHORS
django_treenav-2.0.0.dist-info/LICENSE.txt
django_treenav-2.0.0.dist-info/METADATA
django_treenav-2.0.0.dist-info/WHEEL
django_treenav-2.0.0.dist-info/top_level.txt
django_treenav-2.0.0.dist-info/RECORD
